LICENSE.txt
MANIFEST.in
README.md
setup.cfg
setup.py
src/biblio_laws.egg-info/PKG-INFO
src/biblio_laws.egg-info/SOURCES.txt
src/biblio_laws.egg-info/dependency_links.txt
src/biblio_laws.egg-info/requires.txt
src/biblio_laws.egg-info/top_level.txt
src/bibliolaws/__init__.py
src/bibliolaws/bradford_law.py
src/bibliolaws/datasets.py
src/bibliolaws/lotka_law.py
src/bibliolaws/zipf_law.py
src/bibliolaws/__pycache__/__init__.cpython-36.pyc
src/bibliolaws/__pycache__/bradford_law.cpython-36.pyc
src/bibliolaws/__pycache__/datasets.cpython-36.pyc
src/bibliolaws/__pycache__/lotka_law.cpython-36.pyc
src/bibliolaws/__pycache__/zipf_law.cpython-36.pyc